module_qc_nonelec_gui/__init__.py
module_qc_nonelec_gui/__main__.py
module_qc_nonelec_gui/_version.py
module_qc_nonelec_gui/config_modifier.py
module_qc_nonelec_gui/py.typed
module_qc_nonelec_gui/GUI/__init__.py
module_qc_nonelec_gui/GUI/choosetest_win.py
module_qc_nonelec_gui/GUI/componentinfo_win.py
module_qc_nonelec_gui/GUI/connectdb_win.py
module_qc_nonelec_gui/GUI/connectpd_win.py
module_qc_nonelec_gui/GUI/continue_win.py
module_qc_nonelec_gui/GUI/inputatlsn_win.py
module_qc_nonelec_gui/GUI/selectmode_win.py
module_qc_nonelec_gui/GUI/setup_win.py
module_qc_nonelec_gui/GUI/icon/ATLAS-Logo-BW-CMYK-LGBT-simple-transparent.png
module_qc_nonelec_gui/GUI/icon/ATLAS-Logo-Blue-RGB-H_0.jpg
module_qc_nonelec_gui/GUI/icon/Logo-Outline-web-Blue100.png
module_qc_nonelec_gui/GUI/registration_bare_module/README.md
module_qc_nonelec_gui/GUI/registration_bare_module/__init__.py
module_qc_nonelec_gui/GUI/registration_bare_module/bareinfo_win.py
module_qc_nonelec_gui/GUI/registration_bare_module/bareregist_main.py
module_qc_nonelec_gui/GUI/registration_bare_module/bareregist_win.py
module_qc_nonelec_gui/GUI/registration_bare_module/connectpd_win.py
module_qc_nonelec_gui/GUI/registration_bare_module/feinfo_win.py
module_qc_nonelec_gui/GUI/registration_bare_module/initial_win.py
module_qc_nonelec_gui/GUI/registration_bare_module/sensorinfo_win.py
module_qc_nonelec_gui/GUI/registration_bare_module/img/assembledmodule.jpg
module_qc_nonelec_gui/GUI/registration_bare_module/img/baremodule.jpg
module_qc_nonelec_gui/cli/__init__.py
module_qc_nonelec_gui/cli/main.py
module_qc_nonelec_gui/configuration/config_default.json
module_qc_nonelec_gui/configuration/config_quad.json
module_qc_nonelec_gui/configuration/config_triplet_r.json
module_qc_nonelec_gui/configuration/config_triplet_s.json
module_qc_nonelec_gui/dbinterface/README.md
module_qc_nonelec_gui/dbinterface/__init__.py
module_qc_nonelec_gui/dbinterface/db_write.py
module_qc_nonelec_gui/dbinterface/localdb_authenticator.py
module_qc_nonelec_gui-0.0.8.dist-info/METADATA
module_qc_nonelec_gui-0.0.8.dist-info/WHEEL
module_qc_nonelec_gui-0.0.8.dist-info/entry_points.txt
module_qc_nonelec_gui-0.0.8.dist-info/licenses/LICENSE
module_qc_nonelec_gui-0.0.8.dist-info/RECORD
