Metadata-Version: 2.3
Name: module-qc-nonelec-gui
Version: 0.0.8
Summary: GUI to upload Pixel Quality Control tests to ITk Production Database
Project-URL: Documentation, https://module-qc-nonelec-gui.readthedocs.io/
Project-URL: Homepage, https://gitlab.cern.ch/atlas-itk/pixel/module/module-qc-nonelec-gui
Project-URL: Bug Tracker, https://gitlab.cern.ch/atlas-itk/pixel/module/module-qc-nonelec-gui/-/issues
Project-URL: Source, https://gitlab.cern.ch/atlas-itk/pixel/module/module-qc-nonelec-gui
Author-email: Hideyuki Oide <Hideyuki.Oide@cern.ch>, Minoru Hirose <Minoru.Hirose@cern.ch>, Giordon Stark <gstark@cern.ch>, Daiki Sameshima <sameshima@hepmail.phys.se.tmu.ac.jp>, Erika Oshima <ooshima@hepmail.phys.se.tmu.ac.jp>, Yuji Onishi <onishi@cern.ch>
Maintainer-email: Giordon Stark <gstark@cern.ch>, Hideyuki Oide <Hideyuki.Oide@cern.ch>, ATLAS ITk Pixels <atlas-itk-pixel-modules@cern.ch>
License: BSD 3-Clause License
License-File: LICENSE
Classifier: Development Status :: 1 - Planning
Classifier: Intended Audience :: Developers
Classifier: Intended Audience :: Science/Research
Classifier: License :: OSI Approved :: BSD License
Classifier: Operating System :: OS Independent
Classifier: Programming Language :: Python
Classifier: Programming Language :: Python :: 3
Classifier: Programming Language :: Python :: 3 :: Only
Classifier: Programming Language :: Python :: 3.7
Classifier: Programming Language :: Python :: 3.8
Classifier: Programming Language :: Python :: 3.9
Classifier: Programming Language :: Python :: 3.10
Classifier: Topic :: Scientific/Engineering
Requires-Python: >=3.7
Requires-Dist: defect-detection
Requires-Dist: itkdb>=0.4.3
Requires-Dist: jsonschema
Requires-Dist: matplotlib
Requires-Dist: opencv-python-headless<4.3
Requires-Dist: pymongo~=3.12
Requires-Dist: pyqt5; platform_system == 'Darwin'
Requires-Dist: pyqt5; platform_system == 'Linux'
Requires-Dist: requests
Requires-Dist: typer
Requires-Dist: typing-extensions>=3.7; python_version < '3.8'
